Workbook
Name Slicer_Department1: #N/A
Name Slicer_Gender1: #N/A
Name Slicer_JobRole1: #N/A
Name Slicer_MaritalStatus1: #N/A

Sheet Dashboard Final (2)
B2: HR ATTRITION DASHBOARD
B71: Total Karyawan | D71: Jumlah Resign | F71: Attrition Rate | H71: Overtime Rate (Leavers)
B72: =Helper!A7 -> 1470 | D72: =Helper!B7 -> 237 | F72: =Helper!C7 -> 0.16122449 | H72: =Helper!D7 -> 0.53586498
B76: Metric | C76: Leavers | D76: Stayers
B77: Age | C77: =CUBEVALUE("ThisWorkbookDataModel","[Measures].[Avg Age Leavers]") -> 33.751055 | D77: =CUBEVALUE("ThisWorkbookDataModel","[Measures].[Avg Age Stayers]") -> 37.501217
B78: Tenure | C78: =CUBEVALUE("ThisWorkbookDataModel","[Measures].[Avg Tenure Leavers]") -> 5.1139241 | D78: =CUBEVALUE("ThisWorkbookDataModel","[Measures].[Avg Tenure Stayers]") -> 7.3130576
B79: Income | C79: =CUBEVALUE("ThisWorkbookDataModel","[Measures].[Avg Income Leavers]") -> 45861.523 | D79: =CUBEVALUE("ThisWorkbookDataModel","[Measures].[Avg Income Stayers]") -> 65313.915
B80: Overtime Rate | C80: =CUBEVALUE("ThisWorkbookDataModel","[Measures].[Overtime Rate Leavers]") -> 0.53586498 | D80: =CUBEVALUE("ThisWorkbookDataModel","[Measures].[Overtime Rate Stayers]") -> 0.23438767
B81: Job Satisfaction | C81: =CUBEVALUE("ThisWorkbookDataModel","[Measures].[Avg Job Satisfaction Leavers]") -> 2.4683544 | D81: =CUBEVALUE("ThisWorkbookDataModel","[Measures].[Avg Job Satisfaction Stayers]") -> 2.7785888
B82: Work Life Balance | C82: =CUBEVALUE("ThisWorkbookDataModel","[Measures].[Avg Work Life Balance Leavers]") -> 2.6582278 | D82: =CUBEVALUE("ThisWorkbookDataModel","[Measures].[Avg Work Life Balance Stayers]") -> 2.7810219
B83: Environment Satisfaction | C83: =CUBEVALUE("ThisWorkbookDataModel","[Measures].[Avg Environment Satisfaction Leavers]") -> 2.464135 | D83: =CUBEVALUE("ThisWorkbookDataModel","[Measures].[Avg Environment Satisfaction Stayers]") -> 2.7712895
B84: Job Involvement | C84: =CUBEVALUE("ThisWorkbookDataModel","[Measures].[Avg Job Involvement Leavers]") -> 2.5189873 | D84: =CUBEVALUE("ThisWorkbookDataModel","[Measures].[Avg Job Involvement Stayers]") -> 2.7704785

Sheet Dashboard Final
B2: HR ATTRITION DASHBOARD
V15: Total Karyawan | X15: Jumlah Resign | Z15: Attrition Rate | AB15: Overtime Rate (Leavers)
V16: =Helper!A7 -> 1470 | X16: =Helper!B7 -> 237 | Z16: =Helper!C7 -> 0.16122449 | AB16: =Helper!D7 -> 0.53586498
V20: Metric | W20: Leavers | X20: Stayers
V21: Age | W21: =CUBEVALUE("ThisWorkbookDataModel","[Measures].[Avg Age Leavers]") -> 33.751055 | X21: =CUBEVALUE("ThisWorkbookDataModel","[Measures].[Avg Age Stayers]") -> 37.501217
V22: Tenure | W22: =CUBEVALUE("ThisWorkbookDataModel","[Measures].[Avg Tenure Leavers]") -> 5.1139241 | X22: =CUBEVALUE("ThisWorkbookDataModel","[Measures].[Avg Tenure Stayers]") -> 7.3130576
V23: Income | W23: =CUBEVALUE("ThisWorkbookDataModel","[Measures].[Avg Income Leavers]") -> 45861.523 | X23: =CUBEVALUE("ThisWorkbookDataModel","[Measures].[Avg Income Stayers]") -> 65313.915
V24: Overtime Rate | W24: =CUBEVALUE("ThisWorkbookDataModel","[Measures].[Overtime Rate Leavers]") -> 0.53586498 | X24: =CUBEVALUE("ThisWorkbookDataModel","[Measures].[Overtime Rate Stayers]") -> 0.23438767
V25: Job Satisfaction | W25: =CUBEVALUE("ThisWorkbookDataModel","[Measures].[Avg Job Satisfaction Leavers]") -> 2.4683544 | X25: =CUBEVALUE("ThisWorkbookDataModel","[Measures].[Avg Job Satisfaction Stayers]") -> 2.7785888
V26: Work Life Balance | W26: =CUBEVALUE("ThisWorkbookDataModel","[Measures].[Avg Work Life Balance Leavers]") -> 2.6582278 | X26: =CUBEVALUE("ThisWorkbookDataModel","[Measures].[Avg Work Life Balance Stayers]") -> 2.7810219
V27: Environment Satisfaction | W27: =CUBEVALUE("ThisWorkbookDataModel","[Measures].[Avg Environment Satisfaction Leavers]") -> 2.464135 | X27: =CUBEVALUE("ThisWorkbookDataModel","[Measures].[Avg Environment Satisfaction Stayers]") -> 2.7712895
V28: Job Involvement | W28: =CUBEVALUE("ThisWorkbookDataModel","[Measures].[Avg Job Involvement Leavers]") -> 2.5189873 | X28: =CUBEVALUE("ThisWorkbookDataModel","[Measures].[Avg Job Involvement Stayers]") -> 2.7704785

Sheet Helper
A3: Avg Tenure Leavers | B3: Avg Tenure Stayers | C3: Avg Income Leavers | D3: Avg Income Stayers | E3: Avg Years Since Promotion Leavers | F3: Avg Years Since Promotion Stayers | G3: Avg Age Leavers | H3: Avg Age Stayers | I3: Avg Salary Hike Leavers | J3: Avg Salary Hike Stayers | K3: Avg Total Working Years Leavers | L3: Avg Total Working Years Stayers | M3: Avg Years In Current Role Leavers | N3: Avg Years In Current Role Stayers | O3: Avg Job Satisfaction Leavers | P3: Avg Job Satisfaction Stayers | Q3: Avg Work Life Balance Leavers | R3: Avg Work Life Balance Stayers | S3: Avg Environment Satisfaction Leavers | T3: Avg Environment Satisfaction Stayers | U3: Avg Job Involvement Leavers | V3: Avg Job Involvement Stayers | W3: Overtime Rate Leavers | X3: Overtime Rate Stayers | Y3: Avg Distance Leavers | Z3: Avg Distance Stayers
A4: 5.1139241 | B4: 7.3130576 | C4: 45861.523 | D4: 65313.915 | E4: 1.9451477 | F4: 2.2343877 | G4: 33.751055 | H4: 37.501217 | I4: 15.097046 | J4: 15.231144 | K4: 8.2447257 | L4: 11.862936 | M4: 2.9029536 | N4: 4.4841849 | O4: 2.4683544 | P4: 2.7785888 | Q4: 2.6582278 | R4: 2.7810219 | S4: 2.464135 | T4: 2.7712895 | U4: 2.5189873 | V4: 2.7704785 | W4: 0.53586498 | X4: 0.23438767 | Y4: 10.599156 | Z4: 8.8751014
A6: Headcount | B6: Attrition Count | C6: Attrition Rate | D6: Overtime Rate Leavers
A7: 1470 | B7: 237 | C7: 0.16122449 | D7: 0.53586498
A9: Row Labels | B9: Headcount | C9: Attrition Rate
A10: Sales | B10: 442 | C10: 0.20588235
A11: Human Resources | B11: 62 | C11: 0.19354839
A12: Research & Development | B12: 966 | C12: 0.13871636
A13: Grand Total | B13: 1470 | C13: 0.16122449
A15: Row Labels | B15: Headcount | C15: Attrition Rate
A16: Human Resources | B16: 27 | C16: 0.25925926
A17: Technical Degree | B17: 132 | C17: 0.24242424
A18: Marketing | B18: 152 | C18: 0.21710526
A19: Life Sciences | B19: 629 | C19: 0.14944356
A20: Medical | B20: 451 | C20: 0.13525499
A21: Other | B21: 79 | C21: 0.12658228
A22: Grand Total | B22: 1470 | C22: 0.16122449
A24: Row Labels | B24: Headcount | C24: Attrition Rate
A25: Single | B25: 470 | C25: 0.25531915
A26: Married | B26: 673 | C26: 0.12481426
A27: Divorced | B27: 327 | C27: 0.10091743
A28: Grand Total | B28: 1470 | C28: 0.16122449
A30: Row Labels | B30: Headcount | C30: Attrition Rate
A31: Sales Representative | B31: 82 | C31: 0.40243902
A32: Laboratory Technician | B32: 252 | C32: 0.24206349
A33: Human Resources | B33: 52 | C33: 0.23076923
A34: Sales Executive | B34: 343 | C34: 0.16909621
A35: Research Scientist | B35: 288 | C35: 0.16319444
A36: Manufacturing Director | B36: 143 | C36: 0.06993007
A37: Healthcare Representative | B37: 129 | C37: 0.069767442
A38: Manager | B38: 102 | C38: 0.049019608
A39: Research Director | B39: 79 | C39: 0.025316456
A40: Grand Total | B40: 1470 | C40: 0.16122449

Sheet Dim_EducationField

Sheet Dim_Department

Sheet Dim_JobRole

Sheet Fact_Employee

Sheet HR_Employee_Attrition_Clean
A1: Age | B1: Attrition | C1: BusinessTravel | D1: DailyRate | E1: Department | F1: DistanceFromHome | G1: Education | H1: EducationField | I1: EmployeeNumber | J1: EnvironmentSatisfaction | K1: Gender | L1: HourlyRate | M1: JobInvolvement | N1: JobLevel | O1: JobRole | P1: JobSatisfaction | Q1: MaritalStatus | R1: MonthlyIncome | S1: MonthlyRate | T1: NumCompaniesWorked | U1: OverTime | V1: PercentSalaryHike | W1: PerformanceRating | X1: RelationshipSatisfaction | Y1: StockOptionLevel | Z1: TotalWorkingYears | AA1: TrainingTimesLastYear | AB1: WorkLifeBalance | AC1: YearsAtCompany | AD1: YearsInCurrentRole | AE1: YearsSinceLastPromotion | AF1: YearsWithCurrManager | AG1: JoinDate
A2: 44 | B2: No | C2: Non-Travel | D2: 489 | E2: Research & Development | F2: 23 | G2: Bachelor | H2: Medical | I2: 132 | J2: Medium | K2: Male | L2: 67 | M2: High | N2: Junior Level | O2: Laboratory Technician | P2: Medium | Q2: Married | R2: 20420 | S2: 25043 | T2: 4 | U2: No | V2: 12 | W2: Excellent | X2: High | Y2: 1 | Z2: 17 | AA2: 3 | AB2: Best | AC2: 3 | AD2: 2 | AE2: 1 | AF2: 2 | AG2: 44662
A3: 21 | B3: Yes | C3: Travel_Frequently | D3: 251 | E3: Research & Development | F3: 10 | G3: College | H3: Life Sciences | I3: 1279 | J3: Low | K3: Female | L3: 45 | M3: Medium | N3: Entry Level | O3: Laboratory Technician | P3: High | Q3: Single | R3: 26250 | S3: 25308 | T3: 1 | U3: No | V3: 20 | W3: Outstanding | X3: High | Y3: 0 | Z3: 2 | AA3: 2 | AB3: Bad | AC3: 2 | AD3: 2 | AE3: 2 | AF3: 2 | AG3: 42358
A4: 23 | B4: No | C4: Travel_Rarely | D4: 160 | E4: Research & Development | F4: 4 | G4: Below College | H4: Medical | I4: 1735 | J4: High | K4: Female | L4: 51 | M4: High | N4: Entry Level | O4: Laboratory Technician | P4: Medium | Q4: Single | R4: 32950 | S4: 12862 | T4: 1 | U4: No | V4: 13 | W4: Excellent | X4: High | Y4: 0 | Z4: 3 | AA4: 3 | AB4: Bad | AC4: 3 | AD4: 2 | AE4: 1 | AF4: 2 | AG4: 43140
A5: 26 | B5: Yes | C5: Travel_Rarely | D5: 1449 | E5: Research & Development | F5: 16 | G5: Master | H5: Medical | I5: 394 | J5: Low | K5: Male | L5: 45 | M5: High | N5: Entry Level | O5: Laboratory Technician | P5: Medium | Q5: Divorced | R5: 23730 | S5: 14180 | T5: 2 | U5: Yes | V5: 13 | W5: Excellent | X5: Very High | Y5: 1 | Z5: 5 | AA5: 2 | AB5: Better | AC5: 3 | AD5: 2 | AE5: 0 | AF5: 2 | AG5: 43171
A6: 32 | B6: Yes | C6: Travel_Rarely | D6: 515 | E6: Research & Development | F6: 1 | G6: Bachelor | H6: Life Sciences | I6: 331 | J6: Very High | K6: Male | L6: 62 | M6: Medium | N6: Entry Level | O6: Laboratory Technician | P6: High | Q6: Single | R6: 37300 | S6: 9571 | T6: 0 | U6: Yes | V6: 14 | W6: Excellent | X6: Very High | Y6: 0 | Z6: 4 | AA6: 2 | AB6: Bad | AC6: 3 | AD6: 2 | AE6: 1 | AF6: 2 | AG6: 42758
A7: 30 | B7: Yes | C7: Travel_Rarely | D7: 945 | E7: Sales | F7: 9 | G7: Bachelor | H7: Medical | I7: 1876 | J7: Medium | K7: Male | L7: 89 | M7: High | N7: Entry Level | O7: Sales Representative | P7: Very High | Q7: Single | R7: 10810 | S7: 16019 | T7: 1 | U7: No | V7: 13 | W7: Excellent | X7: High | Y7: 0 | Z7: 1 | AA7: 3 | AB7: Good | AC7: 1 | AD7: 0 | AE7: 0 | AF7: 0 | AG7: 42434
A8: 51 | B8: No | C8: Travel_Rarely | D8: 1318 | E8: Sales | F8: 26 | G8: Master | H8: Marketing | I8: 851 | J8: Low | K8: Female | L8: 66 | M8: High | N8: Senior Level | O8: Manager | P8: High | Q8: Married | R8: 163070 | S8: 5594 | T8: 2 | U8: No | V8: 14 | W8: Excellent | X8: High | Y8: 1 | Z8: 29 | AA8: 2 | AB8: Good | AC8: 20 | AD8: 6 | AE8: 4 | AF8: 17 | AG8: 42486
A9: 48 | B9: No | C9: Non-Travel | D9: 1262 | E9: Research & Development | F9: 1 | G9: Master | H9: Life Sciences | I9: 1116 | J9: Low | K9: Male | L9: 35 | M9: Very High | N9: Senior Level | O9: Manager | P9: Very High | Q9: Single | R9: 168850 | S9: 16154 | T9: 2 | U9: No | V9: 22 | W9: Outstanding | X9: High | Y9: 0 | Z9: 27 | AA9: 3 | AB9: Good | AC9: 5 | AD9: 4 | AE9: 2 | AF9: 1 | AG9: 43773
A10: 55 | B10: No | C10: Non-Travel | D10: 177 | E10: Research & Development | F10: 8 | G10: Below College | H10: Medical | I10: 1278 | J10: Very High | K10: Male | L10: 37 | M10: Medium | N10: Senior Level | O10: Healthcare Representative | P10: Medium | Q10: Divorced | R10: 135770 | S10: 25592 | T10: 1 | U10: Yes | V10: 15 | W10: Excellent | X10: Very High | Y10: 1 | Z10: 34 | AA10: 3 | AB10: Better | AC10: 33 | AD10: 9 | AE10: 15 | AF10: 0 | AG10: 44905
A11: 32 | B11: No | C11: Travel_Rarely | D11: 334 | E11: Research & Development | F11: 5 | G11: College | H11: Life Sciences | I11: 21 | J11: Low | K11: Male | L11: 80 | M11: Very High | N11: Entry Level | O11: Research Scientist | P11: Medium | Q11: Divorced | R11: 32980 | S11: 15053 | T11: 0 | U11: Yes | V11: 12 | W11: Excellent | X11: Very High | Y11: 2 | Z11: 7 | AA11: 5 | AB11: Good | AC11: 6 | AD11: 2 | AE11: 0 | AF11: 5 | AG11: 44121
A12: 33 | B12: No | C12: Travel_Rarely | D12: 867 | E12: Research & Development | F12: 8 | G12: Master | H12: Life Sciences | I12: 1798 | J12: Very High | K12: Male | L12: 90 | M12: Very High | N12: Entry Level | O12: Research Scientist | P12: Low | Q12: Married | R12: 31430 | S12: 6076 | T12: 6 | U12: No | V12: 19 | W12: Excellent | X12: Medium | Y12: 1 | Z12: 14 | AA12: 1 | AB12: Better | AC12: 10 | AD12: 8 | AE12: 7 | AF12: 6 | AG12: 43264
A13: 45 | B13: No | C13: Travel_Rarely | D13: 252 | E13: Research & Development | F13: 2 | G13: Bachelor | H13: Life Sciences | I13: 834 | J13: Medium | K13: Female | L13: 95 | M13: Medium | N13: Entry Level | O13: Research Scientist | P13: High | Q13: Single | R13: 22740 | S13: 6153 | T13: 1 | U13: No | V13: 14 | W13: Excellent | X13: Very High | Y13: 0 | Z13: 1 | AA13: 3 | AB13: Better | AC13: 1 | AD13: 0 | AE13: 0 | AF13: 0 | AG13: 42378
... A1471: 22 | B1471: Yes | C1471: Travel_Rarely | D1471: 1294 | E1471: Research & Development | F1471: 8 | G1471: Below College | H1471: Medical | I1471: 1783 | J1471: High | K1471: Female | L1471: 79 | M1471: High | N1471: Entry Level | O1471: Laboratory Technician | P1471: Low | Q1471: Married | R1471: 23980 | S1471: 15999 | T1471: 1 | U1471: Yes | V1471: 17 | W1471: Excellent | X1471: High | Y1471: 0 | Z1471: 1 | AA1471: 6 | AB1471: Better | AC1471: 1 | AD1471: 0 | AE1471: 0 | AF1471: 0 | AG1471: 43969

Sheet Descriptive_Stats
A1: Age | B1: DailyRate | C1: DistanceFromHome | D1: HourlyRate | E1: MonthlyIncome | F1: MonthlyRate | G1: NumCompaniesWorked | H1: PercentSalaryHike | I1: StockOptionLevel | J1: TotalWorkingYears | K1: TrainingTimesLastYear | L1: YearsAtCompany | M1: YearsInCurrentRole | N1: YearsSinceLastPromotion | O1: YearsWithCurrManager | Q1: Age | S1: DailyRate | U1: DistanceFromHome | W1: HourlyRate | Y1: MonthlyIncome | AA1: MonthlyRate | AC1: NumCompaniesWorked | AE1: PercentSalaryHike | AG1: StockOptionLevel | AI1: TotalWorkingYears | AK1: TrainingTimesLastYear | AM1: YearsAtCompany | AO1: YearsInCurrentRole | AQ1: YearsSinceLastPromotion | AS1: YearsWithCurrManager
A2: 44 | B2: 489 | C2: 23 | D2: 67 | E2: 20420 | F2: 25043 | G2: 4 | H2: 12 | I2: 1 | J2: 17 | K2: 3 | L2: 3 | M2: 2 | N2: 1 | O2: 2
A3: 21 | B3: 251 | C3: 10 | D3: 45 | E3: 26250 | F3: 25308 | G3: 1 | H3: 20 | I3: 0 | J3: 2 | K3: 2 | L3: 2 | M3: 2 | N3: 2 | O3: 2 | Q3: Mean | R3: 36.896599 | S3: Mean | T3: 802.48571 | U3: Mean | V3: 9.1530612 | W3: Mean | X3: 65.891156 | Y3: Mean | Z3: 62177.713 | AA3: Mean | AB3: 14313.103 | AC3: Mean | AD3: 2.6931973 | AE3: Mean | AF3: 15.209524 | AG3: Mean | AH3: 0.79387755 | AI3: Mean | AJ3: 11.279592 | AK3: Mean | AL3: 2.7993197 | AM3: Mean | AN3: 6.9585034 | AO3: Mean | AP3: 4.2292517 | AQ3: Mean | AR3: 2.1877551 | AS3: Mean | AT3: 4.1231293
A4: 23 | B4: 160 | C4: 4 | D4: 51 | E4: 32950 | F4: 12862 | G4: 1 | H4: 13 | I4: 0 | J4: 3 | K4: 3 | L4: 3 | M4: 2 | N4: 1 | O4: 2 | Q4: Standard Error | R4: 0.2354683 | S4: Standard Error | T4: 10.524335 | U4: Standard Error | V4: 0.21052164 | W4: Standard Error | X4: 0.53023267 | Y4: Standard Error | Z4: 1226.3169 | AA4: Standard Error | AB4: 185.64628 | AC4: Standard Error | AD4: 0.065153137 | AE4: Standard Error | AF4: 0.095458593 | AG4: Standard Error | AH4: 0.022223886 | AI4: Standard Error | AJ4: 0.20293855 | AK4: Standard Error | AL4: 0.033626791 | AM4: Standard Error | AN4: 0.1580417 | AO4: Standard Error | AP4: 0.094498756 | AQ4: Standard Error | AR4: 0.084047512 | AS4: Standard Error | AT4: 0.093064221
A5: 26 | B5: 1449 | C5: 16 | D5: 45 | E5: 23730 | F5: 14180 | G5: 2 | H5: 13 | I5: 1 | J5: 5 | K5: 2 | L5: 3 | M5: 2 | N5: 0 | O5: 2 | Q5: Median | R5: 36 | S5: Median | T5: 802 | U5: Median | V5: 7 | W5: Median | X5: 66 | Y5: Median | Z5: 47745 | AA5: Median | AB5: 14235.5 | AC5: Median | AD5: 2 | AE5: Median | AF5: 14 | AG5: Median | AH5: 1 | AI5: Median | AJ5: 10 | AK5: Median | AL5: 3 | AM5: Median | AN5: 5 | AO5: Median | AP5: 3 | AQ5: Median | AR5: 1 | AS5: Median | AT5: 3
A6: 32 | B6: 515 | C6: 1 | D6: 62 | E6: 37300 | F6: 9571 | G6: 0 | H6: 14 | I6: 0 | J6: 4 | K6: 2 | L6: 3 | M6: 2 | N6: 1 | O6: 2 | Q6: Mode | R6: 36 | S6: Mode | T6: 691 | U6: Mode | V6: 2 | W6: Mode | X6: 66 | Y6: Mode | Z6: 61340 | AA6: Mode | AB6: 9150 | AC6: Mode | AD6: 1 | AE6: Mode | AF6: 11 | AG6: Mode | AH6: 0 | AI6: Mode | AJ6: 10 | AK6: Mode | AL6: 2 | AM6: Mode | AN6: 5 | AO6: Mode | AP6: 2 | AQ6: Mode | AR6: 0 | AS6: Mode | AT6: 2
A7: 30 | B7: 945 | C7: 9 | D7: 89 | E7: 10810 | F7: 16019 | G7: 1 | H7: 13 | I7: 0 | J7: 1 | K7: 3 | L7: 1 | M7: 0 | N7: 0 | O7: 0 | Q7: Standard Deviation | R7: 9.0279908 | S7: Standard Deviation | T7: 403.5091 | U7: Standard Deviation | V7: 8.0715217 | W7: Standard Deviation | X7: 20.329428 | Y7: Standard Deviation | Z7: 47017.699 | AA7: Standard Deviation | AB7: 7117.786 | AC7: Standard Deviation | AD7: 2.498009 | AE7: Standard Deviation | AF7: 3.6599377 | AG7: Standard Deviation | AH7: 0.85207667 | AI7: Standard Deviation | AJ7: 7.7807817 | AK7: Standard Deviation | AL7: 1.2892706 | AM7: Standard Deviation | AN7: 6.0594102 | AO7: Standard Deviation | AP7: 3.623137 | AQ7: Standard Deviation | AR7: 3.2224303 | AS7: Standard Deviation | AT7: 3.5681361
A8: 51 | B8: 1318 | C8: 26 | D8: 66 | E8: 163070 | F8: 5594 | G8: 2 | H8: 14 | I8: 1 | J8: 29 | K8: 2 | L8: 20 | M8: 6 | N8: 4 | O8: 17 | Q8: Sample Variance | R8: 81.504617 | S8: Sample Variance | T8: 162819.59 | U8: Sample Variance | V8: 65.149463 | W8: Sample Variance | X8: 413.28563 | Y8: Sample Variance | Z8: 2.210664e+09 | AA8: Sample Variance | AB8: 50662878 | AC8: Sample Variance | AD8: 6.240049 | AE8: Sample Variance | AF8: 13.395144 | AG8: Sample Variance | AH8: 0.72603465 | AI8: Sample Variance | AJ8: 60.540563 | AK8: Sample Variance | AL8: 1.6622187 | AM8: Sample Variance | AN8: 36.716452 | AO8: Sample Variance | AP8: 13.127122 | AQ8: Sample Variance | AR8: 10.384057 | AS8: Sample Variance | AT8: 12.731595
A9: 48 | B9: 1262 | C9: 1 | D9: 35 | E9: 168850 | F9: 16154 | G9: 2 | H9: 22 | I9: 0 | J9: 27 | K9: 3 | L9: 5 | M9: 4 | N9: 2 | O9: 1 | Q9: Kurtosis | R9: -0.32619413 | S9: Kurtosis | T9: -1.2038228 | U9: Kurtosis | V9: -0.1743193 | W9: Kurtosis | X9: -1.1963985 | Y9: Kurtosis | Z9: 1.1449586 | AA9: Kurtosis | AB9: -1.2149561 | AC9: Kurtosis | AD9: 0.010213817 | AE9: Kurtosis | AF9: -0.30059822 | AG9: Kurtosis | AH9: 0.36463433 | AI9: Kurtosis | AJ9: 0.91826954 | AK9: Kurtosis | AL9: 0.49499299 | AM9: Kurtosis | AN9: 4.2346648 | AO9: Kurtosis | AP9: 0.47742077 | AQ9: Kurtosis | AR9: 3.6126731 | AS9: Kurtosis | AT9: 0.17105808
A10: 55 | B10: 177 | C10: 8 | D10: 37 | E10: 135770 | F10: 25592 | G10: 1 | H10: 15 | I10: 1 | J10: 34 | K10: 3 | L10: 33 | M10: 9 | N10: 15 | O10: 0 | Q10: Skewness | R10: 0.42859517 | S10: Skewness | T10: -0.0035185684 | U10: Skewness | V10: 0.97703656 | W10: Skewness | X10: -0.032310953 | Y10: Skewness | Z10: 1.3731393 | AA10: Skewness | AB10: 0.018577808 | AC10: Skewness | AD10: 1.0264711 | AE10: Skewness | AF10: 0.82112798 | AG10: Skewness | AH10: 0.96898032 | AI10: Skewness | AJ10: 1.1171719 | AK10: Skewness | AL10: 0.55312417 | AM10: Skewness | AN10: 1.8220489 | AO10: Skewness | AP10: 0.91736316 | AQ10: Skewness | AR10: 1.98429 | AS10: Skewness | AT10: 0.83345099
A11: 32 | B11: 334 | C11: 5 | D11: 80 | E11: 32980 | F11: 15053 | G11: 0 | H11: 12 | I11: 2 | J11: 7 | K11: 5 | L11: 6 | M11: 2 | N11: 0 | O11: 5 | Q11: Range | R11: 42 | S11: Range | T11: 1397 | U11: Range | V11: 28 | W11: Range | X11: 70 | Y11: Range | Z11: 198939 | AA11: Range | AB11: 24905 | AC11: Range | AD11: 9 | AE11: Range | AF11: 14 | AG11: Range | AH11: 3 | AI11: Range | AJ11: 40 | AK11: Range | AL11: 6 | AM11: Range | AN11: 40 | AO11: Range | AP11: 18 | AQ11: Range | AR11: 15 | AS11: Range | AT11: 17
A12: 33 | B12: 867 | C12: 8 | D12: 90 | E12: 31430 | F12: 6076 | G12: 6 | H12: 19 | I12: 1 | J12: 14 | K12: 1 | L12: 10 | M12: 8 | N12: 7 | O12: 6 | Q12: Minimum | R12: 18 | S12: Minimum | T12: 102 | U12: Minimum | V12: 1 | W12: Minimum | X12: 30 | Y12: Minimum | Z12: 1051 | AA12: Minimum | AB12: 2094 | AC12: Minimum | AD12: 0 | AE12: Minimum | AF12: 11 | AG12: Minimum | AH12: 0 | AI12: Minimum | AJ12: 0 | AK12: Minimum | AL12: 0 | AM12: Minimum | AN12: 0 | AO12: Minimum | AP12: 0 | AQ12: Minimum | AR12: 0 | AS12: Minimum | AT12: 0
A13: 45 | B13: 252 | C13: 2 | D13: 95 | E13: 22740 | F13: 6153 | G13: 1 | H13: 14 | I13: 0 | J13: 1 | K13: 3 | L13: 1 | M13: 0 | N13: 0 | O13: 0 | Q13: Maximum | R13: 60 | S13: Maximum | T13: 1499 | U13: Maximum | V13: 29 | W13: Maximum | X13: 100 | Y13: Maximum | Z13: 199990 | AA13: Maximum | AB13: 26999 | AC13: Maximum | AD13: 9 | AE13: Maximum | AF13: 25 | AG13: Maximum | AH13: 3 | AI13: Maximum | AJ13: 40 | AK13: Maximum | AL13: 6 | AM13: Maximum | AN13: 40 | AO13: Maximum | AP13: 18 | AQ13: Maximum | AR13: 15 | AS13: Maximum | AT13: 17
A14: 34 | B14: 999 | C14: 26 | D14: 92 | E14: 20290 | F14: 15891 | G14: 1 | H14: 20 | I14: 3 | J14: 5 | K14: 2 | L14: 5 | M14: 4 | N14: 0 | O14: 0 | Q14: Sum | R14: 54238 | S14: Sum | T14: 1179654 | U14: Sum | V14: 13455 | W14: Sum | X14: 96860 | Y14: Sum | Z14: 91401238 | AA14: Sum | AB14: 21040262 | AC14: Sum | AD14: 3959 | AE14: Sum | AF14: 22358 | AG14: Sum | AH14: 1167 | AI14: Sum | AJ14: 16581 | AK14: Sum | AL14: 4115 | AM14: Sum | AN14: 10229 | AO14: Sum | AP14: 6217 | AQ14: Sum | AR14: 3216 | AS14: Sum | AT14: 6061
A15: 31 | B15: 330 | C15: 22 | D15: 98 | E15: 61790 | F15: 21057 | G15: 1 | H15: 15 | I15: 2 | J15: 10 | K15: 3 | L15: 10 | M15: 2 | N15: 6 | O15: 7 | Q15: Count | R15: 1470 | S15: Count | T15: 1470 | U15: Count | V15: 1470 | W15: Count | X15: 1470 | Y15: Count | Z15: 1470 | AA15: Count | AB15: 1470 | AC15: Count | AD15: 1470 | AE15: Count | AF15: 1470 | AG15: Count | AH15: 1470 | AI15: Count | AJ15: 1470 | AK15: Count | AL15: 1470 | AM15: Count | AN15: 1470 | AO15: Count | AP15: 1470 | AQ15: Count | AR15: 1470 | AS15: Count | AT15: 1470
A16: 49 | B16: 1091 | C16: 1 | D16: 90 | E16: 139640 | F16: 17810 | G16: 7 | H16: 12 | I16: 0 | J16: 25 | K16: 2 | L16: 7 | M16: 1 | N16: 0 | O16: 7
A17: 52 | B17: 1325 | C17: 11 | D17: 82 | E17: 31490 | F17: 21821 | G17: 8 | H17: 20 | I17: 1 | J17: 9 | K17: 3 | L17: 5 | M17: 2 | N17: 1 | O17: 4
A18: 58 | B18: 1272 | C18: 5 | D18: 37 | E18: 105520 | F18: 9255 | G18: 2 | H18: 13 | I18: 1 | J18: 24 | K18: 3 | L18: 6 | M18: 0 | N18: 0 | O18: 4
A19: 38 | B19: 653 | C19: 29 | D19: 50 | E19: 24060 | F19: 5456 | G19: 1 | H19: 11 | I19: 0 | J19: 10 | K19: 2 | L19: 10 | M19: 3 | N19: 9 | O19: 9
A20: 38 | B20: 201 | C20: 10 | D20: 99 | E20: 132060 | F20: 3376 | G20: 3 | H20: 12 | I20: 1 | J20: 20 | K20: 3 | L20: 18 | M20: 16 | N20: 1 | O20: 11
A21: 30 | B21: 855 | C21: 7 | D21: 73 | E21: 47790 | F21: 12761 | G21: 7 | H21: 14 | I21: 2 | J21: 8 | K21: 3 | L21: 3 | M21: 2 | N21: 0 | O21: 2
A22: 34 | B22: 1003 | C22: 2 | D22: 95 | E22: 40330 | F22: 15834 | G22: 2 | H22: 11 | I22: 0 | J22: 5 | K22: 3 | L22: 3 | M22: 2 | N22: 0 | O22: 2
A23: 36 | B23: 1450 | C23: 15 | D23: 52 | E23: 190810 | F23: 10849 | G23: 5 | H23: 11 | I23: 1 | J23: 25 | K23: 2 | L23: 5 | M23: 2 | N23: 0 | O23: 3
A24: 39 | B24: 203 | C24: 2 | D24: 84 | E24: 121690 | F24: 13547 | G24: 7 | H24: 11 | I24: 3 | J24: 21 | K24: 4 | L24: 18 | M24: 7 | N24: 11 | O24: 5
A25: 48 | B25: 1221 | C25: 7 | D25: 96 | E25: 54860 | F25: 24795 | G25: 4 | H25: 11 | I25: 3 | J25: 15 | K25: 3 | L25: 2 | M25: 2 | N25: 2 | O25: 2
A26: 36 | B26: 676 | C26: 1 | D26: 35 | E26: 52280 | F26: 23361 | G26: 0 | H26: 15 | I26: 1 | J26: 10 | K26: 2 | L26: 9 | M26: 7 | N26: 0 | O26: 5
A27: 57 | B27: 210 | C27: 29 | D27: 56 | E27: 141180 | F27: 22102 | G27: 3 | H27: 12 | I27: 1 | J27: 32 | K27: 3 | L27: 1 | M27: 0 | N27: 0 | O27: 0
... A1471: 22 | B1471: 1294 | C1471: 8 | D1471: 79 | E1471: 23980 | F1471: 15999 | G1471: 1 | H1471: 17 | I1471: 0 | J1471: 1 | K1471: 6 | L1471: 1 | M1471: 0 | N1471: 0 | O1471: 0
